tests
scrapy_rethinkdb
