Metadata-Version: 1.1
Name: scrapy-rethinkdb
Version: 0.0.4
Summary: Scrapy pipeline for rethinkdb.
Home-page: https://github.com/sprij/scrapy-rethinkdb
Author: sprij
Author-email: s.rijo@yahoo.com
License: UNKNOWN
Keywords: scrapy pipeline rethinkdb
Platform: UNKNOWN
Classifier: Development Status :: 3 - Alpha
Classifier: Topic :: Utilities
Classifier: Programming Language :: Python
Classifier: Intended Audience :: Developers
Classifier: License :: OSI Approved :: GNU General Public License v2 (GPLv2)
